functools.py
setup.py
micropython_functools.egg-info/PKG-INFO
micropython_functools.egg-info/SOURCES.txt
micropython_functools.egg-info/dependency_links.txt
micropython_functools.egg-info/top_level.txt